{
    "moduleId": "keyword-coverage",
    "brandId": "brand-1",
    "timestamp": "2024-12-23T14:30:00Z",
    "overallScore": 71,
    "scoreTrend": "down",
    "insights": [
        {
            "title": "Strong Branded Keyword Dominance",
            "description": "You rank #1 for 94% of branded keywords, maintaining strong brand protection.",
            "type": "success"
        },
        {
            "title": "Growing Long-tail Coverage",
            "description": "Non-branded long-tail keyword coverage increased 18% this quarter.",
            "type": "success"
        },
        {
            "title": "Low Non-Branded Coverage",
            "description": "Only 34% coverage for non-branded terms in your core category vs 52% industry average.",
            "type": "critical"
        }
    ],
    "issues": [
        {
            "id": "issue-1",
            "severity": "high",
            "message": "Non-Branded Coverage Gap (34% vs 52%)",
            "impact": "Missing discovery traffic from category-level searches"
        },
        {
            "id": "issue-2",
            "severity": "medium",
            "message": "Keyword Cannibalization (5 Clusters)",
            "impact": "12 pages competing for same keywords, diluting ranking potential"
        },
        {
            "id": "issue-3",
            "severity": "medium",
            "message": "Missing Question Keywords",
            "impact": "Not ranking for common how/what/why queries that AI prioritizes"
        }
    ],
    "recommendations": [
        {
            "title": "Create AI-Optimized Content Clusters",
            "effort": "high",
            "impact": "high",
            "action": "Build comprehensive content hubs around 10 priority non-branded topic clusters."
        },
        {
            "title": "Resolve Cannibalization",
            "effort": "medium",
            "impact": "high",
            "action": "Consolidate competing pages and implement proper internal linking hierarchy."
        },
        {
            "title": "Question-Based Content",
            "effort": "medium",
            "impact": "medium",
            "action": "Create FAQ pages and Q&A content targeting conversational AI queries."
        }
    ]
}